Workbook

Sheet Dashboard
B1: TABLEAU DE BORD — ANALYSE DES VENTES 2023-2024 | S1: Catégorie | T1: CA (€) | V1: Mois | W1: CA 2023 (€) | X1: CA Cumulé 2023 (€)
B2: 200 transactions | 5 vendeurs | 4 catégories | 5 régions | S2: Informatique | T2: =SUMIF(Ventes!E$2:E$201,"Informatique",Ventes!I$2:I$201) -> 298630.9 | V2: Jan | W2: 48824 | X2: 48824
S3: Téléphonie | T3: =SUMIF(Ventes!E$2:E$201,"Téléphonie",Ventes!I$2:I$201) -> 151093.7 | V3: Fév | W3: 26931 | X3: 75755
S4: Accessoires | T4: =SUMIF(Ventes!E$2:E$201,"Accessoires",Ventes!I$2:I$201) -> 0 | V4: Mar | W4: 26719 | X4: 102474
B5: CA TOTAL LIVRÉ | F5: COMMANDES LIVRÉES | J5: MARGE MOYENNE (%) | N5: TAUX D'ANNULATION | S5: Logiciels | T5: =SUMIF(Ventes!E$2:E$201,"Logiciels",Ventes!I$2:I$201) -> 0 | V5: Avr | W5: 41781 | X5: 144255
B6: =SUMIF(Ventes!L2:L201,"Livré",Ventes!I2:I201) -> 322336.3 | F6: =COUNTIF(Ventes!L2:L201,"Livré") -> 145 | J6: =AVERAGEIF(Ventes!L2:L201,"Livré",Ventes!K2:K201) -> 30.2 | N6: =COUNTIF(Ventes!L2:L201,"Annulé")/COUNTA(Ventes!B2:B201)*100 -> 13.5 | V6: Mai | W6: 42511 | X6: 186766
V7: Jun | W7: 42919 | X7: 229685
S8: Vendeur | T8: CA (€) | V8: Jul | W8: 54399 | X8: 284084
B9: sur 200 transactions | F9: sur 200 transactions | J9: sur 200 transactions | N9: sur 200 transactions | S9: Alice Martin | T9: =SUMIF(Ventes!C$2:C$201,"Alice Martin",Ventes!I$2:I$201) -> 171973.65 | V9: Aoû | W9: 34120 | X9: 318204
S10: Bruno Lefèvre | T10: =SUMIF(Ventes!C$2:C$201,"Bruno Lefèvre",Ventes!I$2:I$201) -> 195732.05 | V10: Sep | W10: 32751 | X10: 350955
B11: CA PAR CATÉGORIE | I11: PERFORMANCE DES VENDEURS | S11: Camille Dubois | T11: =SUMIF(Ventes!C$2:C$201,"Camille Dubois",Ventes!I$2:I$201) -> 82018.9 | V11: Oct | W11: 39154 | X11: 390109
S12: David Moreau | T12: =SUMIF(Ventes!C$2:C$201,"David Moreau",Ventes!I$2:I$201) -> 0 | V12: Nov | W12: 35137 | X12: 425246
S13: Emma Bernard | T13: =SUMIF(Ventes!C$2:C$201,"Emma Bernard",Ventes!I$2:I$201) -> 0 | V13: Déc | W13: 24477 | X13: 449723
S15: Région | T15: CA (€) | V15: Canal | W15: CA (€)
S16: Île-de-France | T16: =SUMIF(Ventes!D$2:D$201,"Île-de-France",Ventes!I$2:I$201) -> 184438.1 | V16: E-commerce | W16: 211556
S17: Auvergne-Rhône-Alpes | T17: =SUMIF(Ventes!D$2:D$201,"Auvergne-Rhône-Alpes",Ventes!I$2:I$201) -> 176913.1 | V17: Boutique | W17: 238169
S18: Nouvelle-Aquitaine | T18: =SUMIF(Ventes!D$2:D$201,"Nouvelle-Aquitaine",Ventes!I$2:I$201) -> 88373.4
S19: Occitanie | T19: =SUMIF(Ventes!D$2:D$201,"Occitanie",Ventes!I$2:I$201) -> 0
S20: Bretagne | T20: =SUMIF(Ventes!D$2:D$201,"Bretagne",Ventes!I$2:I$201) -> 0
S22: Statut | T22: Nb
S23: Livré | T23: =COUNTIF(Ventes!L$2:L$201,"Livré") -> 145
S24: En cours | T24: =COUNTIF(Ventes!L$2:L$201,"En cours") -> 28
S25: Annulé | T25: =COUNTIF(Ventes!L$2:L$201,"Annulé") -> 27
B27: CA PAR RÉGION | I27: RÉPARTITION : STATUT & CANAL | S27: Canal | T27: CA (€)
S28: E-commerce | T28: =SUMIF(Ventes!M$2:M$201,"E-commerce",Ventes!I$2:I$201) -> 211555.85
S29: Boutique | T29: =SUMIF(Ventes!M$2:M$201,"Boutique",Ventes!I$2:I$201) -> 238168.75
S30: Téléphone | T30: =SUMIF(Ventes!M$2:M$201,"Téléphone",Ventes!I$2:I$201) -> 0
S31: Revendeur | T31: =SUMIF(Ventes!M$2:M$201,"Revendeur",Ventes!I$2:I$201) -> 0
B46: 📅 ÉVOLUTION DU CA MENSUEL | I46: 🛒 CA PAR CANAL DE VENTE

Sheet Ventes
A1: Date | B1: ID Commande | C1: Vendeur | D1: Région | E1: Catégorie | F1: Produit | G1: Quantité | H1: Prix Unitaire (€) | I1: CA (€) | J1: Remise (%) | K1: Marge (%) | L1: Statut | M1: Canal de Vente
A2: 19/01/2023 | B2: CMD-0001 | C2: Camille Dubois | D2: Île-de-France | E2: Téléphonie | F2: Smartphone X12 | G2: 5 | H2: 799 | I2: 3995 | J2: 0 | K2: 32.5 | L2: Livré | M2: E-commerce
A3: 22/10/2023 | B3: CMD-0002 | C3: Alice Martin | D3: Île-de-France | E3: Informatique | F3: Laptop Pro 15 | G3: 5 | H3: 1299 | I3: 6495 | J3: 0 | K3: 27.8 | L3: Livré | M3: E-commerce
A4: 45176 | B4: CMD-0003 | C4: Alice Martin | D4: Île-de-France | E4: Informatique | F4: Laptop Pro 15 | G4: 5 | H4: 1299 | I4: 6495 | J4: 0 | K4: 34 | L4: Livré | M4: E-commerce
A5: 45051 | B5: CMD-0004 | C5: Alice Martin | D5: Auvergne-Rhône-Alpes | E5: Informatique | F5: Tablette HD | G5: 1 | H5: 449 | I5: 449 | J5: 0 | K5: 34.3 | L5: Livré | M5: Boutique
A6: 25/11/2023 | B6: CMD-0005 | C6: Alice Martin | D6: Île-de-France | E6: Téléphonie | F6: Smartphone Y8 | G6: 3 | H6: 499 | I6: 1497 | J6: 0 | K6: 25.2 | L6: Livré | M6: Boutique
A7: 45113 | B7: CMD-0006 | C7: Bruno Lefèvre | D7: Île-de-France | E7: Informatique | F7: Laptop Air 13 | G7: 5 | H7: 899 | I7: 4495 | J7: 0 | K7: 32.8 | L7: Livré | M7: Boutique
A8: 44937 | B8: CMD-0007 | C8: Bruno Lefèvre | D8: Auvergne-Rhône-Alpes | E8: Téléphonie | F8: Smartphone X12 | G8: 1 | H8: 799 | I8: 799 | J8: 0 | K8: 27.6 | L8: Livré | M8: E-commerce
A9: 31/07/2023 | B9: CMD-0008 | C9: Bruno Lefèvre | D9: Île-de-France | E9: Informatique | F9: Laptop Pro 15 | G9: 1 | H9: 1299 | I9: 1299 | J9: 0 | K9: 33.7 | L9: En cours | M9: Boutique
A10: 44991 | B10: CMD-0009 | C10: Bruno Lefèvre | D10: Auvergne-Rhône-Alpes | E10: Informatique | F10: Laptop Air 13 | G10: 4 | H10: 899 | I10: 3596 | J10: 0 | K10: 34.8 | L10: Livré | M10: E-commerce
A11: 44989 | B11: CMD-0010 | C11: Camille Dubois | D11: Auvergne-Rhône-Alpes | E11: Informatique | F11: Laptop Air 13 | G11: 2 | H11: 899 | I11: 1708.1 | J11: 5 | K11: 28.1 | L11: Livré | M11: E-commerce
A12: 45143 | B12: CMD-0011 | C12: Alice Martin | D12: Auvergne-Rhône-Alpes | E12: Téléphonie | F12: Smartphone Y8 | G12: 5 | H12: 499 | I12: 2495 | J12: 0 | K12: 26.5 | L12: Livré | M12: E-commerce
A13: 25/05/2023 | B13: CMD-0012 | C13: Bruno Lefèvre | D13: Nouvelle-Aquitaine | E13: Téléphonie | F13: Smartphone Y8 | G13: 5 | H13: 499 | I13: 2495 | J13: 0 | K13: 26.7 | L13: Livré | M13: Boutique
A14: 45084 | B14: CMD-0013 | C14: Camille Dubois | D14: Auvergne-Rhône-Alpes | E14: Téléphonie | F14: Smartphone X12 | G14: 4 | H14: 799 | I14: 3196 | J14: 0 | K14: 34.5 | L14: Annulé | M14: Boutique
A15: 21/06/2023 | B15: CMD-0014 | C15: Alice Martin | D15: Île-de-France | E15: Téléphonie | F15: Smartphone Y8 | G15: 4 | H15: 499 | I15: 1896.2 | J15: 5 | K15: 26.3 | L15: Livré | M15: Boutique
A16: 45018 | B16: CMD-0015 | C16: Alice Martin | D16: Auvergne-Rhône-Alpes | E16: Informatique | F16: Laptop Pro 15 | G16: 3 | H16: 1299 | I16: 3702.15 | J16: 5 | K16: 35 | L16: En cours | M16: E-commerce
A17: 44969 | B17: CMD-0016 | C17: Bruno Lefèvre | D17: Île-de-France | E17: Téléphonie | F17: Écouteurs Sans Fil | G17: 4 | H17: 179 | I17: 716 | J17: 0 | K17: 31.8 | L17: En cours | M17: E-commerce
A18: 45084 | B18: CMD-0017 | C18: Bruno Lefèvre | D18: Nouvelle-Aquitaine | E18: Téléphonie | F18: Smartphone Y8 | G18: 4 | H18: 499 | I18: 1996 | J18: 0 | K18: 34.4 | L18: Livré | M18: E-commerce
A19: 44986 | B19: CMD-0018 | C19: Alice Martin | D19: Auvergne-Rhône-Alpes | E19: Informatique | F19: Laptop Air 13 | G19: 1 | H19: 899 | I19: 899 | J19: 0 | K19: 34.3 | L19: Livré | M19: E-commerce
A20: 18/01/2023 | B20: CMD-0019 | C20: Alice Martin | D20: Nouvelle-Aquitaine | E20: Informatique | F20: Tablette HD | G20: 4 | H20: 449 | I20: 1796 | J20: 0 | K20: 30.1 | L20: Livré | M20: Boutique
A21: 20/02/2023 | B21: CMD-0020 | C21: Alice Martin | D21: Île-de-France | E21: Téléphonie | F21: Écouteurs Sans Fil | G21: 1 | H21: 179 | I21: 170.05 | J21: 5 | K21: 33.2 | L21: Livré | M21: Boutique
A22: 21/10/2023 | B22: CMD-0021 | C22: Bruno Lefèvre | D22: Auvergne-Rhône-Alpes | E22: Téléphonie | F22: Écouteurs Sans Fil | G22: 5 | H22: 179 | I22: 895 | J22: 0 | K22: 31.6 | L22: Livré | M22: Boutique
A23: 27/10/2023 | B23: CMD-0022 | C23: Bruno Lefèvre | D23: Île-de-France | E23: Informatique | F23: Laptop Pro 15 | G23: 5 | H23: 1299 | I23: 6495 | J23: 0 | K23: 30 | L23: Livré | M23: E-commerce
A24: 45112 | B24: CMD-0023 | C24: Bruno Lefèvre | D24: Auvergne-Rhône-Alpes | E24: Informatique | F24: Laptop Air 13 | G24: 5 | H24: 899 | I24: 4495 | J24: 0 | K24: 32.1 | L24: Livré | M24: Boutique
A25: 19/07/2023 | B25: CMD-0024 | C25: Alice Martin | D25: Île-de-France | E25: Téléphonie | F25: Smartphone Y8 | G25: 5 | H25: 499 | I25: 2495 | J25: 0 | K25: 31.3 | L25: Livré | M25: E-commerce
A26: 45108 | B26: CMD-0025 | C26: Camille Dubois | D26: Île-de-France | E26: Informatique | F26: Laptop Pro 15 | G26: 5 | H26: 1299 | I26: 6170.25 | J26: 5 | K26: 31 | L26: Annulé | M26: E-commerce
A27: 28/03/2023 | B27: CMD-0026 | C27: Camille Dubois | D27: Nouvelle-Aquitaine | E27: Informatique | F27: Laptop Air 13 | G27: 1 | H27: 899 | I27: 899 | J27: 0 | K27: 32.9 | L27: Livré | M27: E-commerce
A28: 28/03/2023 | B28: CMD-0027 | C28: Bruno Lefèvre | D28: Auvergne-Rhône-Alpes | E28: Informatique | F28: Laptop Pro 15 | G28: 2 | H28: 1299 | I28: 2598 | J28: 0 | K28: 29.7 | L28: Livré | M28: E-commerce
A29: 45026 | B29: CMD-0028 | C29: Camille Dubois | D29: Île-de-France | E29: Informatique | F29: Laptop Pro 15 | G29: 1 | H29: 1299 | I29: 1299 | J29: 0 | K29: 26.4 | L29: Annulé | M29: E-commerce
A30: 23/10/2023 | B30: CMD-0029 | C30: Bruno Lefèvre | D30: Île-de-France | E30: Informatique | F30: Tablette HD | G30: 3 | H30: 449 | I30: 1347 | J30: 0 | K30: 35 | L30: Livré | M30: Boutique
A31: 45141 | B31: CMD-0030 | C31: Alice Martin | D31: Île-de-France | E31: Informatique | F31: Laptop Air 13 | G31: 4 | H31: 899 | I31: 3596 | J31: 0 | K31: 29.6 | L31: Livré | M31: Boutique
A32: 24/11/2023 | B32: CMD-0031 | C32: Camille Dubois | D32: Auvergne-Rhône-Alpes | E32: Téléphonie | F32: Smartphone X12 | G32: 2 | H32: 799 | I32: 1598 | J32: 0 | K32: 30.2 | L32: En cours | M32: Boutique
A33: 45234 | B33: CMD-0032 | C33: Alice Martin | D33: Auvergne-Rhône-Alpes | E33: Téléphonie | F33: Smartphone Y8 | G33: 1 | H33: 499 | I33: 499 | J33: 0 | K33: 26 | L33: Livré | M33: Boutique
A34: 15/11/2023 | B34: CMD-0033 | C34: Alice Martin | D34: Île-de-France | E34: Informatique | F34: Laptop Pro 15 | G34: 5 | H34: 1299 | I34: 6495 | J34: 0 | K34: 29.3 | L34: Livré | M34: Boutique
A35: 45207 | B35: CMD-0034 | C35: Alice Martin | D35: Île-de-France | E35: Informatique | F35: Laptop Air 13 | G35: 3 | H35: 899 | I35: 2697 | J35: 0 | K35: 27.8 | L35: En cours | M35: E-commerce
A36: 25/06/2023 | B36: CMD-0035 | C36: Camille Dubois | D36: Nouvelle-Aquitaine | E36: Informatique | F36: Laptop Air 13 | G36: 2 | H36: 899 | I36: 1708.1 | J36: 5 | K36: 25.4 | L36: Annulé | M36: Boutique
A37: 21/06/2023 | B37: CMD-0036 | C37: Bruno Lefèvre | D37: Île-de-France | E37: Informatique | F37: Laptop Pro 15 | G37: 5 | H37: 1299 | I37: 6495 | J37: 0 | K37: 25.1 | L37: Livré | M37: Boutique
A38: 44927 | B38: CMD-0037 | C38: Bruno Lefèvre | D38: Auvergne-Rhône-Alpes | E38: Téléphonie | F38: Smartphone X12 | G38: 1 | H38: 799 | I38: 799 | J38: 0 | K38: 32 | L38: En cours | M38: E-commerce
A39: 17/09/2023 | B39: CMD-0038 | C39: Bruno Lefèvre | D39: Nouvelle-Aquitaine | E39: Téléphonie | F39: Smartphone X12 | G39: 1 | H39: 799 | I39: 799 | J39: 0 | K39: 27.6 | L39: Livré | M39: E-commerce
A40: 45205 | B40: CMD-0039 | C40: Alice Martin | D40: Île-de-France | E40: Informatique | F40: Laptop Pro 15 | G40: 4 | H40: 1299 | I40: 4936.2 | J40: 5 | K40: 30.5 | L40: En cours | M40: E-commerce
A41: 29/11/2023 | B41: CMD-0040 | C41: Alice Martin | D41: Auvergne-Rhône-Alpes | E41: Téléphonie | F41: Écouteurs Sans Fil | G41: 5 | H41: 179 | I41: 895 | J41: 0 | K41: 32.8 | L41: Livré | M41: Boutique
A42: 45047 | B42: CMD-0041 | C42: Camille Dubois | D42: Auvergne-Rhône-Alpes | E42: Informatique | F42: Tablette HD | G42: 3 | H42: 449 | I42: 1279.65 | J42: 5 | K42: 30.3 | L42: Livré | M42: E-commerce
A43: 29/10/2023 | B43: CMD-0042 | C43: Bruno Lefèvre | D43: Nouvelle-Aquitaine | E43: Téléphonie | F43: Smartphone X12 | G43: 3 | H43: 799 | I43: 2277.15 | J43: 5 | K43: 27.1 | L43: En cours | M43: Boutique
A44: 45139 | B44: CMD-0043 | C44: Camille Dubois | D44: Auvergne-Rhône-Alpes | E44: Informatique | F44: Laptop Air 13 | G44: 2 | H44: 899 | I44: 1798 | J44: 0 | K44: 29.1 | L44: Livré | M44: E-commerce
A45: 20/08/2023 | B45: CMD-0044 | C45: Bruno Lefèvre | D45: Auvergne-Rhône-Alpes | E45: Informatique | F45: Tablette HD | G45: 4 | H45: 449 | I45: 1796 | J45: 0 | K45: 28 | L45: Livré | M45: E-commerce
A46: 15/12/2023 | B46: CMD-0045 | C46: Bruno Lefèvre | D46: Auvergne-Rhône-Alpes | E46: Informatique | F46: Laptop Pro 15 | G46: 3 | H46: 1299 | I46: 3897 | J46: 0 | K46: 29 | L46: Livré | M46: E-commerce
A47: 45117 | B47: CMD-0046 | C47: Alice Martin | D47: Auvergne-Rhône-Alpes | E47: Informatique | F47: Tablette HD | G47: 3 | H47: 449 | I47: 1347 | J47: 0 | K47: 31.7 | L47: Livré | M47: E-commerce
A48: 44961 | B48: CMD-0047 | C48: Bruno Lefèvre | D48: Auvergne-Rhône-Alpes | E48: Informatique | F48: Laptop Pro 15 | G48: 4 | H48: 1299 | I48: 5196 | J48: 0 | K48: 30.7 | L48: Livré | M48: Boutique
A49: 30/11/2023 | B49: CMD-0048 | C49: Alice Martin | D49: Auvergne-Rhône-Alpes | E49: Téléphonie | F49: Smartphone X12 | G49: 1 | H49: 799 | I49: 799 | J49: 0 | K49: 34.5 | L49: Livré | M49: E-commerce
A50: 45146 | B50: CMD-0049 | C50: Alice Martin | D50: Auvergne-Rhône-Alpes | E50: Informatique | F50: Tablette HD | G50: 5 | H50: 449 | I50: 2245 | J50: 0 | K50: 27 | L50: Livré | M50: Boutique
A51: 21/07/2023 | B51: CMD-0050 | C51: Bruno Lefèvre | D51: Nouvelle-Aquitaine | E51: Informatique | F51: Laptop Pro 15 | G51: 3 | H51: 1299 | I51: 3897 | J51: 0 | K51: 27.3 | L51: Livré | M51: E-commerce
A52: 21/02/2023 | B52: CMD-0051 | C52: Camille Dubois | D52: Nouvelle-Aquitaine | E52: Informatique | F52: Laptop Air 13 | G52: 3 | H52: 899 | I52: 2562.15 | J52: 5 | K52: 28.4 | L52: Livré | M52: Boutique
A53: 25/03/2023 | B53: CMD-0052 | C53: Bruno Lefèvre | D53: Auvergne-Rhône-Alpes | E53: Informatique | F53: Laptop Pro 15 | G53: 1 | H53: 1299 | I53: 1299 | J53: 0 | K53: 30.7 | L53: En cours | M53: Boutique
A54: 27/05/2023 | B54: CMD-0053 | C54: Bruno Lefèvre | D54: Nouvelle-Aquitaine | E54: Informatique | F54: Tablette HD | G54: 4 | H54: 449 | I54: 1796 | J54: 0 | K54: 34.2 | L54: Annulé | M54: E-commerce
A55: 28/03/2023 | B55: CMD-0054 | C55: Bruno Lefèvre | D55: Nouvelle-Aquitaine | E55: Informatique | F55: Laptop Air 13 | G55: 1 | H55: 899 | I55: 854.05 | J55: 5 | K55: 27.8 | L55: Annulé | M55: Boutique
A56: 27/11/2023 | B56: CMD-0055 | C56: Bruno Lefèvre | D56: Auvergne-Rhône-Alpes | E56: Informatique | F56: Laptop Pro 15 | G56: 3 | H56: 1299 | I56: 3897 | J56: 0 | K56: 31.8 | L56: Livré | M56: Boutique
A57: 13/09/2023 | B57: CMD-0056 | C57: Camille Dubois | D57: Île-de-France | E57: Informatique | F57: Laptop Pro 15 | G57: 5 | H57: 1299 | I57: 6495 | J57: 0 | K57: 33 | L57: En cours | M57: Boutique
A58: 16/04/2023 | B58: CMD-0057 | C58: Bruno Lefèvre | D58: Auvergne-Rhône-Alpes | E58: Téléphonie | F58: Smartphone Y8 | G58: 4 | H58: 499 | I58: 1896.2 | J58: 5 | K58: 35 | L58: Livré | M58: E-commerce
A59: 15/10/2023 | B59: CMD-0058 | C59: Camille Dubois | D59: Auvergne-Rhône-Alpes | E59: Informatique | F59: Laptop Air 13 | G59: 2 | H59: 899 | I59: 1708.1 | J59: 5 | K59: 33.1 | L59: Livré | M59: Boutique
A60: 24/03/2023 | B60: CMD-0059 | C60: Bruno Lefèvre | D60: Île-de-France | E60: Informatique | F60: Tablette HD | G60: 1 | H60: 449 | I60: 449 | J60: 0 | K60: 32.1 | L60: Livré | M60: Boutique
A61: 15/06/2023 | B61: CMD-0060 | C61: Alice Martin | D61: Auvergne-Rhône-Alpes | E61: Informatique | F61: Laptop Air 13 | G61: 2 | H61: 899 | I61: 1798 | J61: 0 | K61: 26.8 | L61: Livré | M61: Boutique
A62: 45176 | B62: CMD-0061 | C62: Alice Martin | D62: Île-de-France | E62: Téléphonie | F62: Smartphone X12 | G62: 1 | H62: 799 | I62: 799 | J62: 0 | K62: 31.6 | L62: Livré | M62: Boutique
A63: 44968 | B63: CMD-0062 | C63: Camille Dubois | D63: Île-de-France | E63: Informatique | F63: Tablette HD | G63: 4 | H63: 449 | I63: 1796 | J63: 0 | K63: 25.6 | L63: Livré | M63: Boutique
A64: 45202 | B64: CMD-0063 | C64: Bruno Lefèvre | D64: Île-de-France | E64: Téléphonie | F64: Smartphone X12 | G64: 1 | H64: 799 | I64: 799 | J64: 0 | K64: 30.1 | L64: En cours | M64: Boutique
A65: 25/02/2023 | B65: CMD-0064 | C65: Alice Martin | D65: Auvergne-Rhône-Alpes | E65: Informatique | F65: Tablette HD | G65: 5 | H65: 449 | I65: 2132.75 | J65: 5 | K65: 29.5 | L65: Annulé | M65: E-commerce
A66: 45144 | B66: CMD-0065 | C66: Bruno Lefèvre | D66: Île-de-France | E66: Informatique | F66: Laptop Air 13 | G66: 5 | H66: 899 | I66: 4270.25 | J66: 5 | K66: 32.3 | L66: Livré | M66: E-commerce
A67: 26/04/2023 | B67: CMD-0066 | C67: Alice Martin | D67: Auvergne-Rhône-Alpes | E67: Informatique | F67: Laptop Air 13 | G67: 4 | H67: 899 | I67: 3416.2 | J67: 5 | K67: 34.3 | L67: Livré | M67: E-commerce
A68: 45242 | B68: CMD-0067 | C68: Camille Dubois | D68: Auvergne-Rhône-Alpes | E68: Téléphonie | F68: Écouteurs Sans Fil | G68: 5 | H68: 179 | I68: 895 | J68: 0 | K68: 34.8 | L68: Annulé | M68: Boutique
A69: 45088 | B69: CMD-0068 | C69: Alice Martin | D69: Île-de-France | E69: Téléphonie | F69: Smartphone Y8 | G69: 5 | H69: 499 | I69: 2495 | J69: 0 | K69: 33.1 | L69: Annulé | M69: Boutique
A70: 29/07/2023 | B70: CMD-0069 | C70: Alice Martin | D70: Auvergne-Rhône-Alpes | E70: Téléphonie | F70: Smartphone X12 | G70: 2 | H70: 799 | I70: 1598 | J70: 0 | K70: 30 | L70: Livré | M70: E-commerce
A71: 45268 | B71: CMD-0070 | C71: Bruno Lefèvre | D71: Île-de-France | E71: Téléphonie | F71: Smartphone Y8 | G71: 2 | H71: 499 | I71: 998 | J71: 0 | K71: 34.9 | L71: Livré | M71: Boutique
A72: 23/09/2023 | B72: CMD-0071 | C72: Bruno Lefèvre | D72: Nouvelle-Aquitaine | E72: Informatique | F72: Tablette HD | G72: 2 | H72: 449 | I72: 898 | J72: 0 | K72: 25.6 | L72: Livré | M72: Boutique
A73: 45084 | B73: CMD-0072 | C73: Bruno Lefèvre | D73: Nouvelle-Aquitaine | E73: Téléphonie | F73: Smartphone Y8 | G73: 5 | H73: 499 | I73: 2495 | J73: 0 | K73: 32.5 | L73: Livré | M73: E-commerce
A74: 18/11/2023 | B74: CMD-0073 | C74: Alice Martin | D74: Auvergne-Rhône-Alpes | E74: Téléphonie | F74: Smartphone Y8 | G74: 4 | H74: 499 | I74: 1996 | J74: 0 | K74: 29.3 | L74: Livré | M74: E-commerce
A75: 19/06/2023 | B75: CMD-0074 | C75: Alice Martin | D75: Auvergne-Rhône-Alpes | E75: Téléphonie | F75: Smartphone Y8 | G75: 5 | H75: 499 | I75: 2495 | J75: 0 | K75: 30.9 | L75: Livré | M75: Boutique
A76: 27/07/2023 | B76: CMD-0075 | C76: Camille Dubois | D76: Nouvelle-Aquitaine | E76: Informatique | F76: Laptop Pro 15 | G76: 2 | H76: 1299 | I76: 2598 | J76: 0 | K76: 28.2 | L76: Livré | M76: Boutique
A77: 22/01/2023 | B77: CMD-0076 | C77: Camille Dubois | D77: Île-de-France | E77: Téléphonie | F77: Smartphone X12 | G77: 2 | H77: 799 | I77: 1598 | J77: 0 | K77: 32.5 | L77: Livré | M77: Boutique
A78: 44990 | B78: CMD-0077 | C78: Alice Martin | D78: Île-de-France | E78: Informatique | F78: Laptop Air 13 | G78: 1 | H78: 899 | I78: 899 | J78: 0 | K78: 31 | L78: Livré | M78: Boutique
A79: 30/07/2023 | B79: CMD-0078 | C79: Bruno Lefèvre | D79: Île-de-France | E79: Téléphonie | F79: Écouteurs Sans Fil | G79: 3 | H79: 179 | I79: 537 | J79: 0 | K79: 25.9 | L79: Livré | M79: E-commerce
A80: 31/01/2023 | B80: CMD-0079 | C80: Bruno Lefèvre | D80: Île-de-France | E80: Téléphonie | F80: Smartphone X12 | G80: 2 | H80: 799 | I80: 1598 | J80: 0 | K80: 33 | L80: Livré | M80: Boutique
A81: 44965 | B81: CMD-0080 | C81: Bruno Lefèvre | D81: Nouvelle-Aquitaine | E81: Téléphonie | F81: Smartphone Y8 | G81: 5 | H81: 499 | I81: 2495 | J81: 0 | K81: 27.2 | L81: Annulé | M81: E-commerce
A82: 26/04/2023 | B82: CMD-0081 | C82: Bruno Lefèvre | D82: Auvergne-Rhône-Alpes | E82: Informatique | F82: Laptop Pro 15 | G82: 2 | H82: 1299 | I82: 2598 | J82: 0 | K82: 29.7 | L82: Livré | M82: Boutique
A83: 23/03/2023 | B83: CMD-0082 | C83: Bruno Lefèvre | D83: Île-de-France | E83: Téléphonie | F83: Smartphone Y8 | G83: 3 | H83: 499 | I83: 1497 | J83: 0 | K83: 33.1 | L83: En cours | M83: E-commerce
A84: 15/01/2023 | B84: CMD-0083 | C84: Bruno Lefèvre | D84: Auvergne-Rhône-Alpes | E84: Téléphonie | F84: Écouteurs Sans Fil | G84: 1 | H84: 179 | I84: 179 | J84: 0 | K84: 25.9 | L84: Livré | M84: Boutique
A85: 15/04/2023 | B85: CMD-0084 | C85: Camille Dubois | D85: Nouvelle-Aquitaine | E85: Téléphonie | F85: Smartphone Y8 | G85: 4 | H85: 499 | I85: 1996 | J85: 0 | K85: 31.9 | L85: Livré | M85: Boutique
A86: 14/08/2023 | B86: CMD-0085 | C86: Alice Martin | D86: Île-de-France | E86: Téléphonie | F86: Écouteurs Sans Fil | G86: 2 | H86: 179 | I86: 340.1 | J86: 5 | K86: 27.9 | L86: Livré | M86: E-commerce
A87: 45231 | B87: CMD-0086 | C87: Bruno Lefèvre | D87: Nouvelle-Aquitaine | E87: Téléphonie | F87: Smartphone Y8 | G87: 1 | H87: 499 | I87: 499 | J87: 0 | K87: 27.2 | L87: Livré | M87: E-commerce
A88: 45179 | B88: CMD-0087 | C88: Alice Martin | D88: Île-de-France | E88: Informatique | F88: Laptop Pro 15 | G88: 1 | H88: 1299 | I88: 1299 | J88: 0 | K88: 32.3 | L88: En cours | M88: Boutique
A89: 24/02/2023 | B89: CMD-0088 | C89: Alice Martin | D89: Île-de-France | E89: Informatique | F89: Tablette HD | G89: 2 | H89: 449 | I89: 898 | J89: 0 | K89: 27.5 | L89: Livré | M89: E-commerce
A90: 45206 | B90: CMD-0089 | C90: Alice Martin | D90: Auvergne-Rhône-Alpes | E90: Téléphonie | F90: Smartphone Y8 | G90: 2 | H90: 499 | I90: 998 | J90: 0 | K90: 29.1 | L90: Livré | M90: Boutique
A91: 45145 | B91: CMD-0090 | C91: Bruno Lefèvre | D91: Île-de-France | E91: Informatique | F91: Laptop Pro 15 | G91: 1 | H91: 1299 | I91: 1299 | J91: 0 | K91: 31.2 | L91: Livré | M91: Boutique
A92: 14/07/2023 | B92: CMD-0091 | C92: Alice Martin | D92: Nouvelle-Aquitaine | E92: Informatique | F92: Laptop Air 13 | G92: 5 | H92: 899 | I92: 4495 | J92: 0 | K92: 34.8 | L92: Annulé | M92: E-commerce
A93: 18/11/2023 | B93: CMD-0092 | C93: Camille Dubois | D93: Nouvelle-Aquitaine | E93: Informatique | F93: Laptop Pro 15 | G93: 1 | H93: 1299 | I93: 1299 | J93: 0 | K93: 27.8 | L93: Livré | M93: Boutique
A94: 45024 | B94: CMD-0093 | C94: Bruno Lefèvre | D94: Île-de-France | E94: Téléphonie | F94: Écouteurs Sans Fil | G94: 2 | H94: 179 | I94: 340.1 | J94: 5 | K94: 29.5 | L94: Livré | M94: Boutique
A95: 45118 | B95: CMD-0094 | C95: Bruno Lefèvre | D95: Auvergne-Rhône-Alpes | E95: Informatique | F95: Laptop Pro 15 | G95: 2 | H95: 1299 | I95: 2598 | J95: 0 | K95: 25.5 | L95: Livré | M95: Boutique
A96: 45018 | B96: CMD-0095 | C96: Alice Martin | D96: Nouvelle-Aquitaine | E96: Téléphonie | F96: Smartphone Y8 | G96: 4 | H96: 499 | I96: 1996 | J96: 0 | K96: 29 | L96: Livré | M96: Boutique
A97: 21/02/2023 | B97: CMD-0096 | C97: Camille Dubois | D97: Île-de-France | E97: Téléphonie | F97: Écouteurs Sans Fil | G97: 1 | H97: 179 | I97: 179 | J97: 0 | K97: 26.8 | L97: Annulé | M97: Boutique
A98: 15/07/2023 | B98: CMD-0097 | C98: Bruno Lefèvre | D98: Île-de-France | E98: Téléphonie | F98: Écouteurs Sans Fil | G98: 5 | H98: 179 | I98: 895 | J98: 0 | K98: 28.9 | L98: Annulé | M98: E-commerce
A99: 29/11/2023 | B99: CMD-0098 | C99: Camille Dubois | D99: Auvergne-Rhône-Alpes | E99: Informatique | F99: Tablette HD | G99: 4 | H99: 449 | I99: 1796 | J99: 0 | K99: 33.4 | L99: Livré | M99: Boutique
A100: 45081 | B100: CMD-0099 | C100: Alice Martin | D100: Nouvelle-Aquitaine | E100: Informatique | F100: Laptop Air 13 | G100: 3 | H100: 899 | I100: 2697 | J100: 0 | K100: 25.7 | L100: Livré | M100: Boutique
...

Sheet Guide
A1: 🗂️ BASE DE DONNÉES — GUIDE D'UTILISATION
A3: 📋 STRUCTURE DE LA BASE
A4: Colonne | B4: Type | C4: Description
A5: Date | B5: Texte (JJ/MM/AAAA) | C5: Date de la commande
A6: ID Commande | B6: Texte | C6: Identifiant unique CMD-XXXX
A7: Vendeur | B7: Texte | C7: Nom du commercial
A8: Région | B8: Texte | C8: Région de vente (France)
A9: Catégorie | B9: Texte | C9: Catégorie de produit
A10: Produit | B10: Texte | C10: Nom du produit
A11: Quantité | B11: Entier | C11: Nombre d'unités vendues
A12: Prix Unitaire (€) | B12: Décimal | C12: Prix catalogue unitaire
A13: CA (€) | B13: Décimal | C13: Chiffre d'affaires (après remise)
A14: Remise (%) | B14: Entier | C14: Remise appliquée (0, 5, 10, 15, 20%)
A15: Marge (%) | B15: Décimal | C15: Taux de marge brute
... A17: Canal de Vente | B17: Texte | C17: E-commerce / Boutique / Téléphone / Revendeur
A19: 💡 IDÉES DE TABLEAUX DE BORD
A20: Analyse | B20: Mesure | C20: Dimension
A21: CA par mois | B21: SOMME(CA) | C21: Date → Mois
A22: CA par région | B22: SOMME(CA) | C22: Région
A23: Performance vendeurs | B23: SOMME(CA) / NB commandes | C23: Vendeur
A24: Top produits | B24: SOMME(Quantité) / SOMME(CA) | C24: Produit
A25: Répartition par canal | B25: NB commandes / % | C25: Canal de Vente
A26: Évolution marge | B26: MOYENNE(Marge) | C26: Date → Trimestre
A27: Taux d'annulation | B27: NB(Annulé)/Total | C27: Statut
A28: Remise vs Marge | B28: Corrélation | C28: Remise / Marge
